simplepac/__init__.py
simplepac/core.py
simplepac/easylist.py
simplepac/utils.py
simplepac/resources/__init__.py
simplepac/resources/proxy.pac
simplepac/resources/proxy_easylist.pac
simplepac-0.1.dist-info/METADATA
simplepac-0.1.dist-info/RECORD
simplepac-0.1.dist-info/WHEEL
simplepac-0.1.dist-info/entry_points.txt
simplepac-0.1.dist-info/top_level.txt
