Metadata-Version: 2.1
Name: simplepac
Version: 0.1
Summary: Generate a simple pac for proxy and ad-block
Home-page: https://github.com/Taosky/simplepac
Author: Taosky
Author-email: t@firefoxcn.net
License: GPL-3.0
Platform: UNKNOWN
Classifier: Programming Language :: Python :: 3
Classifier: License :: OSI Approved :: GNU General Public License v3 (GPLv3)
Classifier: Operating System :: OS Independent
Requires-Dist: requests (==2.18.4)
Requires-Dist: matplotlib (==2.2.2)
Requires-Dist: numpy (==1.14.3)
Requires-Dist: sklearn
Requires-Dist: scipy (==1.1.0)
